mumee/__init__.py
mumee/classes/__init__.py
mumee/classes/clients/__init__.py
mumee/classes/clients/spotify_metadata_client.py
mumee/classes/clients/ytmusic_metadata_client.py
mumee/classes/config/__init__.py
mumee/classes/config/spotify_options.py
mumee/classes/handlers/__init__.py
mumee/classes/handlers/fetch/__init__.py
mumee/classes/handlers/fetch/spotify_playlist_handler.py
mumee/classes/handlers/fetch/spotify_search_handler.py
mumee/classes/handlers/fetch/spotify_track_handler.py
mumee/classes/handlers/fetch/ytmusic_playlist_handler.py
mumee/classes/handlers/fetch/ytmusic_search_handler.py
mumee/classes/handlers/fetch/ytmusic_track_handler.py
mumee/classes/handlers/search/__init__.py
mumee/classes/handlers/search/spotify_explorer_handler.py
mumee/classes/handlers/search/ytmusic_explorer_handler.py
mumee/data/__init__.py
mumee/data/metadata_clients.py
mumee/data/playlist_metadata.py
mumee/data/search_metadata_command.py
mumee/data/song_metadata.py
mumee/di/__init__.py
mumee/di/dependency_injector.py
mumee/errors/__init__.py
mumee/errors/metadata_client_error.py
mumee/interfaces/__init__.py
mumee/interfaces/base_metadata_client.py
mumee/interfaces/base_metadata_explorer.py
mumee/main.py
mumee/py.typed
mumee-0.0.7.dist-info/LICENSE
mumee-0.0.7.dist-info/METADATA
mumee-0.0.7.dist-info/WHEEL
mumee-0.0.7.dist-info/RECORD
